[
    {
        "toyId" : ObjectId("60e6eaf838bfa48c6fa12f58"),
        "userId": ObjectId("60e71302328d622ce5d38d6f"),
        "content": "Lakada"
    },
    {
        "toyId" : ObjectId("60e6eaf838bfa48c6fa12f58"),
        "userId": ObjectId("60e71347328d622ce5d38da1"),
        "content": "Manana"
    },
    {
        "toyId" : ObjectId("60e6eaf838bfa48c6fa12f5f"),
        "userId": ObjectId("60e71302328d622ce5d38d6f"),
        "content": "Pasiki"
    },
    {
        "toyId" : ObjectId("60e6eaf838bfa48c6fa12f5f"),
        "userId": ObjectId("60e71347328d622ce5d38da1"),
        "content": "Vakaru"
    }
]